<?xml version="1.0" encoding="UTF-8" standalone="no"?>
<!DOCTYPE properties SYSTEM "http://java.sun.com/dtd/properties.dtd">
<properties>
<entry key="profiler.settings.instrument.empty.methods">true</entry>
<entry key="ProfilerCPUSettings_profile_runnables">true</entry>
<entry key="ProfilerCPUSettings_filter_type">2</entry>
<entry key="ProfilerMemorySettings_track_every">10</entry>
<entry key="ProfilerMemorySettings_mode">4</entry>
<entry key="ProfilerCPUSettings_root_classes">com.component.common.annotation.**
com.component.common.dao.**
com.component.common.entity.**
com.component.common.hibernate.util.**
com.component.common.jdbc.util.**
com.component.common.pagination.**
com.component.common.service.**
com.component.common.spring.util.**
com.component.common.util.**
com.component.util.**
com.exception.**
com.module.fileTools.**
com.module.sysadmin.model.entity.**
com.module.sysadmin.model.service.**
com.module.sysadmin.model.view.**
</entry>
<entry key="ProfilerCPUSettings_filter_value">com.component.common.annotation.*,
com.component.common.dao.*,
com.component.common.entity.*,
com.component.common.hibernate.util.*,
com.component.common.jdbc.util.*,
com.component.common.pagination.*,
com.component.common.service.*,
com.component.common.spring.util.*,
com.component.common.util.*,
com.component.util.*,
com.exception.*,
com.module.fileTools.*,
com.module.sysadmin.model.entity.*,
com.module.sysadmin.model.service.*,
com.module.sysadmin.model.view.*</entry>
<entry key="profiler.settings.istrument.getter.setter.methods">true</entry>
<entry key="myeclipse.profiling.mode">0</entry>
<entry key="ProfilerMemorySettings_stacktraces">-1</entry>
</properties>
